.gitignore
.pre-commit-config.yaml
.pylintrc
.readthedocs.yml
CODE_OF_CONDUCT.md
LICENSE
README.rst
README.rst.license
__init__.py
biffobear_as3935.py
pyproject.toml
requirements.txt
setup.py
.github/workflows/build.yml
.github/workflows/release.yml
LICENSES/CC-BY-4.0.txt
LICENSES/MIT.txt
LICENSES/Unlicense.txt
biffobear_circuitpython_as3935.egg-info/PKG-INFO
biffobear_circuitpython_as3935.egg-info/SOURCES.txt
biffobear_circuitpython_as3935.egg-info/dependency_links.txt
biffobear_circuitpython_as3935.egg-info/requires.txt
biffobear_circuitpython_as3935.egg-info/top_level.txt
docs/api.rst
docs/api.rst.license
docs/conf.py
docs/examples.rst
docs/examples.rst.license
docs/index.rst
docs/index.rst.license
docs/_static/favicon.ico
docs/_static/favicon.ico.license
examples/as3935_simpletest.py
tests/__init__.py
tests/test_biffobear_as3935.py
tests/test_board_responses.py
tests/test_i2c_subclass.py
tests/test_spi_interface.py
tests/test_spi_subclass.py