Metadata-Version: 2.1
Name: biffobear-circuitpython-as3935
Version: 2.0.3
Summary: CircuitPython driver library for the AS3935 lightning detector.
Home-page: https://github.com/BiffoBear/Biffobear_CircuitPython_AS3935.git
Author: Martin Stephens
Author-email: 
License: MIT
Keywords: adafruit blinka circuitpython micropython Franklin as3935 lightning detector sensorspi
Platform: UNKNOWN
Classifier: Development Status :: 5 - Production/Stable
Classifier: Intended Audience :: Developers
Classifier: Topic :: Software Development :: Libraries
Classifier: Topic :: System :: Hardware
Classifier: License :: OSI Approved :: MIT License
Classifier: Programming Language :: Python :: 3
Classifier: Programming Language :: Python :: 3.4
Classifier: Programming Language :: Python :: 3.5
